gloe/__init__.py
gloe/_composition_utils.py
gloe/_generic_types.py
gloe/_gloe_graph.py
gloe/_plotting_utils.py
gloe/_transformer_utils.py
gloe/_typing_utils.py
gloe/async_transformer.py
gloe/base_transformer.py
gloe/functional.py
gloe/py.typed
gloe/transformers.py
gloe/utils.py
gloe/collection/__init__.py
gloe/collection/_filter.py
gloe/collection/_filter_async.py
gloe/collection/_map.py
gloe/collection/_map_async.py
gloe/collection/_mapover.py
gloe/collection/_mapover_async.py
gloe/conditional/__init__.py
gloe/conditional/_async_conditioner.py
gloe/conditional/_base_conditioner.py
gloe/conditional/_conditioner.py
gloe/conditional/_if.py
gloe/conditional/_if_then_else.py
gloe/conditional/_implication.py
gloe/ensurer/__init__.py
gloe/ensurer/_ensure.py
gloe/ensurer/_transformer_ensurer.py
gloe/exceptions/__init__.py
gloe/experimental/__init__.py
gloe/experimental/_bridge.py
gloe/gateways/__init__.py
gloe/gateways/_base_gateway.py
gloe/gateways/_gateway_factory.py
gloe/gateways/_parallel.py
gloe/gateways/_sequential.py
gloe-0.7.0.dist-info/LICENSE
gloe-0.7.0.dist-info/METADATA
gloe-0.7.0.dist-info/WHEEL
gloe-0.7.0.dist-info/top_level.txt
gloe-0.7.0.dist-info/RECORD
