Metadata-Version: 2.2
Name: gloe
Version: 0.7.0
Summary: Gloe is a general-purpose library designed to guide developers in expressing their code as a flow.
Author-email: Samir Braga <samirchavess@gmail.com>
Project-URL: Homepage, https://gloe.ideos.com.br
Project-URL: Documentation, https://gloe.ideos.com.br
Project-URL: Issues, https://github.com/ideos/gloe/issues
Project-URL: Repository, https://github.com/ideos/gloe
Classifier: Programming Language :: Python :: 3 :: Only
Classifier: Programming Language :: Python :: 3.9
Classifier: Programming Language :: Python :: 3.10
Classifier: Programming Language :: Python :: 3.11
Classifier: Programming Language :: Python :: 3.12
Classifier: Programming Language :: Python :: 3.13
Classifier: License :: OSI Approved :: Apache Software License
Classifier: Operating System :: OS Independent
Requires-Python: >=3.9
License-File: LICENSE
Requires-Dist: typing_extensions~=4.7
Provides-Extra: plot
Requires-Dist: pygraphviz>=1.11; extra == "plot"
Provides-Extra: types
Requires-Dist: mypy~=1.7.0; extra == "types"
